itertree/__init__.py
itertree/itree_data.py
itertree/itree_filters.py
itertree/itree_getitem.py
itertree/itree_helpers.py
itertree/itree_indepth.py
itertree/itree_main.py
itertree/itree_mathsets.py
itertree/itree_private.py
itertree/examples/__init__.py
itertree/examples/calendar_example.py
itertree/examples/itree_data_models.py
itertree/examples/itree_docu_examples.py
itertree/examples/itree_like_anytree.py
itertree/examples/itree_link_example1.py
itertree/examples/itree_usage_example1.py
itertree/examples/itree_usage_example2.py
itertree/itree_indepth_helpers/__init__.py
itertree/itree_indepth_helpers/itree_indepth_iter.py
itertree/itree_indepth_helpers/itree_indepth_levels.py
itertree/itree_indepth_helpers/itree_indepth_siblings.py
itertree/itree_serializer/__init__.py
itertree/itree_serializer/itree_json_converter.py
itertree/itree_serializer/itree_json_serialize.py
itertree/itree_serializer/itree_render_dot.py
itertree/itree_serializer/itree_renderer.py
itertree-1.2.0.dist-info/licenses/LICENSE
itertree-1.2.0.dist-info/METADATA
itertree-1.2.0.dist-info/WHEEL
itertree-1.2.0.dist-info/top_level.txt
itertree-1.2.0.dist-info/RECORD
