Metadata-Version: 2.4
Name: itertree
Version: 1.2.0
Summary: Python tree structure for data storage and iterations
Home-page: https://github.com/BR1py/itertree
Author: B_R
Author-email: br_development@posteo.org
License: MIT
Project-URL: Bug Tracker, https://github.com/BR1py/itertree/issues
Project-URL: Documentation, https://readthedocs.org/projects/itertree/
Classifier: Programming Language :: Python :: 3
Classifier: License :: OSI Approved :: MIT License
Classifier: Operating System :: OS Independent
Requires-Python: >=3.4
License-File: LICENSE
Dynamic: author
Dynamic: author-email
Dynamic: home-page
Dynamic: license
Dynamic: license-file
Dynamic: summary
